<?xml version="1.0" encoding="UTF-8" ?>
<!DOCTYPE struts PUBLIC
    "-//Apache Software Foundation//DTD Struts Configuration 2.3//EN"
    "http://struts.apache.org/dtds/struts-2.3.dtd">

<struts>
	
	<package name="jpwtt_do/jpwtt/Ticket" namespace="/do/jpwtt/Ticket" extends="entando-default">
		
		<global-results>
            <result name="input" type="tiles">admin.jpwtt.Ticket.Admin.entry</result>
            <result name="opNotAllowed" type="chain">list</result>
            <result name="ticketNotFound" type="chain">list</result>
		</global-results>
		
		<!-- Start - List Operations -->
		<action name="list" class="jpwttTicketFinderAction">
            <result type="tiles">admin.jpwtt.Ticket.Admin.list</result>
        	<interceptor-ref name="entandoDefaultStack"><param name="requestAuth.requiredPermission">jpwttOperator</param></interceptor-ref>
        </action>
        
        <action name="search" class="jpwttTicketFinderAction">
            <result type="tiles">admin.jpwtt.Ticket.Admin.list</result>
        	<interceptor-ref name="entandoDefaultStack"><param name="requestAuth.requiredPermission">jpwttOperator</param></interceptor-ref>
        </action>
		<!-- End - List Operations -->
		
		<!-- Start - Ticket Workflow -->
		<action name="view" class="jpwttTicketAction" method="view">
            <result type="tiles">admin.jpwtt.Ticket.Admin.view</result>
        	<interceptor-ref name="entandoDefaultStack"><param name="requestAuth.requiredPermission">jpwttOperator</param></interceptor-ref>
        </action>
		
		<action name="entry" class="jpwttTicketAction" method="view">
            <result type="tiles">admin.jpwtt.Ticket.Admin.entry</result>
        	<interceptor-ref name="entandoDefaultStack"><param name="requestAuth.requiredPermission">jpwttOperator</param></interceptor-ref>
        </action>
		
		<action name="takeInCharge*" class="jpwttTicketAction" method="takeInCharge">
            <result type="chain">entry</result>
        	<interceptor-ref name="entandoDefaultStack"><param name="requestAuth.requiredPermission">jpwttOperator</param></interceptor-ref>
        </action>
		
		<action name="update*" class="jpwttTicketAction" method="update">
            <result type="chain">entry</result>
        	<interceptor-ref name="entandoDefaultStack"><param name="requestAuth.requiredPermission">jpwttOperator</param></interceptor-ref>
        </action>
		
		<action name="assign*" class="jpwttTicketAction" method="setAssignable">
        	<result type="redirectAction">list</result>
        	<interceptor-ref name="entandoDefaultStack"><param name="requestAuth.requiredPermission">jpwttOperator</param></interceptor-ref>
        </action>
		
		<action name="answer*" class="jpwttTicketAction" method="answer">
            <result type="chain">entry</result>
        	<interceptor-ref name="entandoDefaultStack"><param name="requestAuth.requiredPermission">jpwttOperator</param></interceptor-ref>
        </action>
		
		<action name="release*" class="jpwttTicketAction" method="release">
            <result type="chain">entry</result>
        	<interceptor-ref name="entandoDefaultStack"><param name="requestAuth.requiredPermission">jpwttOperator</param></interceptor-ref>
        </action>
		
		<action name="close*" class="jpwttTicketAction" method="close">
        	<result type="redirectAction">list</result>
        	<interceptor-ref name="entandoDefaultStack"><param name="requestAuth.requiredPermission">jpwttOperator</param></interceptor-ref>
        </action>
        <!-- End - Ticket Workflow -->
	</package>
	
</struts>